ftp/__init__.py
ftp/client.py
ftp/server.py
pulselink-1.0.dist-info/LICENSE
pulselink-1.0.dist-info/METADATA
pulselink-1.0.dist-info/WHEEL
pulselink-1.0.dist-info/top_level.txt
pulselink-1.0.dist-info/RECORD
