Metadata-Version: 2.1
Name: pulselink
Version: 1.0
Summary: A custom Fast Transmission Protocol (FTP) for file transfer using IP and hostname.
Home-page: https://github.com/krishnagopaljha/ftp
Author: Krishna Gopal Jha
Classifier: Programming Language :: Python :: 3
Classifier: License :: OSI Approved 
Classifier: License :: OSI Approved :: Apache Software License
Requires-Python: >=3.6
License-File: LICENSE
